blenderline/__init__.py
blenderline/command_line.py
blenderline/collections/__init__.py
blenderline/collections/background.py
blenderline/collections/base.py
blenderline/collections/hdr.py
blenderline/collections/item.py
blenderline/entries/__init__.py
blenderline/entries/background.py
blenderline/entries/base.py
blenderline/entries/hdr.py
blenderline/entries/item.py
blenderline/generators/__init__.py
blenderline/generators/image.py
blenderline/managers/__init__.py
blenderline/managers/background.py
blenderline/managers/hdr.py
blenderline/managers/item.py
blenderline/managers/scene.py
blenderline/references/__init__.py
blenderline/references/item.py
blenderline/references/path.py
blenderline/scripts/__init__.py
blenderline/scripts/blender/__init__.py
blenderline/scripts/blender/generate.py
blenderline/scripts/python/__init__.py
blenderline/scripts/python/convert.py
blenderline/scripts/python/generate.py
blenderline/scripts/python/converters/__init__.py
blenderline/scripts/python/converters/utils.py
blenderline/scripts/python/converters/yolo_detection.py
blenderline/settings/__init__.py
blenderline/settings/image.py
blenderline-0.1.6.dist-info/LICENSE
blenderline-0.1.6.dist-info/METADATA
blenderline-0.1.6.dist-info/WHEEL
blenderline-0.1.6.dist-info/entry_points.txt
blenderline-0.1.6.dist-info/top_level.txt
blenderline-0.1.6.dist-info/RECORD
