Metadata-Version: 2.1
Name: blenderline
Version: 0.1.6
Summary: A pipeline for generating synthetic production line images
Home-page: https://github.com/MaxvandenHoven/blenderline
Author: Max van den Hoven
Author-email: max.hoven@gmail.com
License: GPLv3
Classifier: License :: OSI Approved :: GNU General Public License v3 (GPLv3)
Classifier: Programming Language :: Python :: 3.10
Classifier: Operating System :: OS Independent
Requires-Python: ==3.10.*
License-File: LICENSE
Requires-Dist: blender-stubs (>=3.12.27)
Requires-Dist: bpy (>=3.5.0)
Requires-Dist: numpy
Requires-Dist: opencv-python
Requires-Dist: pyyaml
Provides-Extra: dev
Requires-Dist: black (>=23.3.0) ; extra == 'dev'
Requires-Dist: isort (>=5.12.0) ; extra == 'dev'
Requires-Dist: flake8 (>=6.0.0) ; extra == 'dev'
Requires-Dist: twine (>=4.0.2) ; extra == 'dev'
Requires-Dist: Sphinx (==6.2.1) ; extra == 'dev'
Requires-Dist: sphinx-autobuild (==2021.3.14) ; extra == 'dev'
Requires-Dist: furo (==2023.5.20) ; extra == 'dev'
Requires-Dist: sphinx-copybutton (==0.5.2) ; extra == 'dev'
Requires-Dist: sphinx-design (==0.4.1) ; extra == 'dev'
